hanabython/__init__.py
hanabython/cli.py
hanabython/hanabython_temp.py
hanabython/Modules/Action.py
hanabython/Modules/ActionClue.py
hanabython/Modules/ActionForfeit.py
hanabython/Modules/ActionPlayCard.py
hanabython/Modules/ActionThrow.py
hanabython/Modules/Board.py
hanabython/Modules/Card.py
hanabython/Modules/CardPublic.py
hanabython/Modules/Clue.py
hanabython/Modules/Color.py
hanabython/Modules/ColorColorless.py
hanabython/Modules/ColorMulticolor.py
hanabython/Modules/Colored.py
hanabython/Modules/Colors.py
hanabython/Modules/Configuration.py
hanabython/Modules/ConfigurationColorContents.py
hanabython/Modules/ConfigurationDeck.py
hanabython/Modules/ConfigurationEmptyClueRule.py
hanabython/Modules/ConfigurationEndRule.py
hanabython/Modules/ConfigurationHandSize.py
hanabython/Modules/DiscardPile.py
hanabython/Modules/DrawPile.py
hanabython/Modules/DrawPilePublic.py
hanabython/Modules/Game.py
hanabython/Modules/Hand.py
hanabython/Modules/HandPublic.py
hanabython/Modules/Player.py
hanabython/Modules/PlayerBase.py
hanabython/Modules/PlayerHumanText.py
hanabython/Modules/PlayerPuppet.py
hanabython/Modules/StringAnsi.py
hanabython/Modules/StringUtils.py
hanabython/Modules/__init__.py
hanabython-0.1.10.dist-info/DESCRIPTION.rst
hanabython-0.1.10.dist-info/METADATA
hanabython-0.1.10.dist-info/RECORD
hanabython-0.1.10.dist-info/WHEEL
hanabython-0.1.10.dist-info/entry_points.txt
hanabython-0.1.10.dist-info/metadata.json
hanabython-0.1.10.dist-info/top_level.txt
tests/__init__.py
tests/test_hanabython.py
