Metadata-Version: 2.0
Name: hanabython
Version: 0.1.10
Summary: A Python implementation of Hanabi, a game by Antoine Bauza
Home-page: https://github.com/francois-durand/hanabython
Author: François Durand
Author-email: fradurand@gmail.com
License: GNU General Public License v3
Keywords: hanabython
Platform: UNKNOWN
Classifier: Development Status :: 2 - Pre-Alpha
Classifier: Intended Audience :: Developers
Classifier: License :: OSI Approved :: GNU General Public License v3 (GPLv3)
Classifier: Natural Language :: English
Classifier: Programming Language :: Python :: 3
Classifier: Programming Language :: Python :: 3.4
Classifier: Programming Language :: Python :: 3.5
Classifier: Programming Language :: Python :: 3.6
Requires-Dist: Click (>=6.0)
Requires-Dist: numpy
Requires-Dist: IPython
Requires-Dist: typing
